XStatic_Angular_lrdragndrop-1.0.2.6-nspkg.pth
xstatic/pkg/angular_lrdragndrop/__init__.py
xstatic/pkg/angular_lrdragndrop/data/lrdragndrop.js
XStatic_Angular_lrdragndrop-1.0.2.6.dist-info/LICENCE
XStatic_Angular_lrdragndrop-1.0.2.6.dist-info/METADATA
XStatic_Angular_lrdragndrop-1.0.2.6.dist-info/WHEEL
XStatic_Angular_lrdragndrop-1.0.2.6.dist-info/namespace_packages.txt
XStatic_Angular_lrdragndrop-1.0.2.6.dist-info/top_level.txt
XStatic_Angular_lrdragndrop-1.0.2.6.dist-info/RECORD
