Metadata-Version: 2.1
Name: XStatic-Angular-lrdragndrop
Version: 1.0.2.6
Summary: Angular-lrdragndrop 1.0.2 (XStatic packaging standard)
Home-page: https://github.com/lorenzofox3/lrDragNDrop
Maintainer: Thai Tran
Maintainer-email: tqtran@us.ibm.com
License: MIT
Keywords: drag-n-drop angular table lrdragndrop xstatic
Platform: any
